cloud_lib
