Metadata-Version: 1.1
Name: cloud-lib
Version: 1.1.0
Summary: Cloud Service Library
Home-page: https://github.com/Akira-Taniguchi/cloud_lib
Author: AkiraTaniguchi
Author-email: dededededaiou2003@yahoo.co.jp
License: MIT
Keywords: amazon google cloud bigquery storage s3 ec2
Platform: UNKNOWN
Classifier: Development Status :: 5 - Production/Stable
Classifier: Programming Language :: Python :: 2.7
Classifier: Intended Audience :: Developers
Classifier: License :: OSI Approved :: MIT License
